zr/__init__.py
zr-0.0.5.dist-info/licenses/LICENSE
zr-0.0.5.dist-info/METADATA
zr-0.0.5.dist-info/WHEEL
zr-0.0.5.dist-info/top_level.txt
zr-0.0.5.dist-info/RECORD
