Metadata-Version: 2.4
Name: zr
Version: 0.0.5
Summary: AdWords reporting tools
Home-page: https://github.com/t-c-w/zr
Author: Thor Whalen
License: apache-2.0
Platform: any
License-File: LICENSE
Dynamic: license-file
